CHANGES.txt
MANIFEST.in
README.txt
setup.cfg
setup.py
src/slapos/__init__.py
src/slapos.recipe.nosqltestbed.egg-info/PKG-INFO
src/slapos.recipe.nosqltestbed.egg-info/SOURCES.txt
src/slapos.recipe.nosqltestbed.egg-info/dependency_links.txt
src/slapos.recipe.nosqltestbed.egg-info/entry_points.txt
src/slapos.recipe.nosqltestbed.egg-info/namespace_packages.txt
src/slapos.recipe.nosqltestbed.egg-info/requires.txt
src/slapos.recipe.nosqltestbed.egg-info/top_level.txt
src/slapos/recipe/__init__.py
src/slapos/recipe/nosqltestbed/__init__.py
src/slapos/recipe/nosqltestbed/template/kumo_gateway_run.in
src/slapos/recipe/nosqltestbed/template/kumo_manager_run.in
src/slapos/recipe/nosqltestbed/template/kumo_server_run.in
src/slapos/recipe/nosqltestbed/template/kumotester_manager_run.in
src/slapos/recipe/nosqltestbed/template/nosqltester_manager_run.in
src/slapos/recipe/nosqltestbed/template/nosqltester_run.in