Metadata-Version: 1.0
Name: slapos.recipe.nosqltestbed
Version: 0.0.8.dev
Summary: ZC Buildout recipe for the No SQL test bed
Home-page: UNKNOWN
Author: UNKNOWN
Author-email: UNKNOWN
License: GPLv3
Keywords: buildout nosqltestbed
Platform: UNKNOWN
Classifier: Framework :: Buildout :: Recipe
Classifier: Programming Language :: Python
